{"inkVersion":20,"root":[[{"->":"main"},["done",{"#f":5,"#n":"g-0"}],null],"done",{"main":["^...","\n","^27/11/67","\n","^Hoje tive uma conversa com o Capitão X.","\n","^Ele bateu na porta do meu quarto, querendo saber como eu estava.","\n","^Disse que eu parecia a pessoa mais cabisbaixa na nave e por isso veio me animar.","\n","^Ficamos comendo chocolate e batendo papo. Descobri do envolvimento entre o Capitão X e o Frederick.","\n","^São amigos de infância, cresceram e estudaram juntos. Eles não costumavam interagir em público, mas pude ver várias fotos dos dois juntos no dia da graduação do Frederick.","\n","^Quem imaginaria que um cara como ele poderia ser um cara tão divertido quanto o das fotos.","\n","^Se ele acordar, talvez eu passe mais tempo conversando com ele.","\n","^Disse pro Capitão X que se ele precisar conversar alguma hora que ele pode contar comigo. Ele agradeceu e foi embora.","\n","done",{"#f":1}],"#f":1}],"listDefs":{}}